AUTHORS.rst
AUTHORS.txt
BUILD.rst
CONTRIBUTING.rst
COPYRIGHT.txt
INSTALL.rst
LICENSE.txt
MANIFEST.in
README.rst
setup.py
tasks.py
src/robot/__init__.py
src/robot/__main__.py
src/robot/errors.py
src/robot/gen.py
src/robot/jarrunner.py
src/robot/libdoc.py
src/robot/pythonpathsetter.py
src/robot/rebot.py
src/robot/run.py
src/robot/testdoc.py
src/robot/tidy.py
src/robot/version.py
src/robot/api/__init__.py
src/robot/api/deco.py
src/robot/api/exceptions.py
src/robot/api/logger.py
src/robot/api/parsing.py
src/robot/conf/__init__.py
src/robot/conf/gatherfailed.py
src/robot/conf/settings.py
src/robot/htmldata/__init__.py
src/robot/htmldata/htmlfilewriter.py
src/robot/htmldata/jartemplate.py
src/robot/htmldata/jsonwriter.py
src/robot/htmldata/normaltemplate.py
src/robot/htmldata/template.py
src/robot/htmldata/common/doc_formatting.css
src/robot/htmldata/common/js_disabled.css
src/robot/htmldata/common/storage.js
src/robot/htmldata/lib/jquery.highlight.min.js
src/robot/htmldata/lib/jquery.min.js
src/robot/htmldata/lib/jquery.tablesorter.min.js
src/robot/htmldata/lib/jquery.tmpl.min.js
src/robot/htmldata/lib/jsxcompressor.min.js
src/robot/htmldata/libdoc/doc_formatting.css
src/robot/htmldata/libdoc/libdoc.css
src/robot/htmldata/libdoc/libdoc.html
src/robot/htmldata/libdoc/print.css
src/robot/htmldata/libdoc/pygments.css
src/robot/htmldata/rebot/common.css
src/robot/htmldata/rebot/doc_formatting.css
src/robot/htmldata/rebot/fileloading.js
src/robot/htmldata/rebot/log.css
src/robot/htmldata/rebot/log.html
src/robot/htmldata/rebot/log.js
src/robot/htmldata/rebot/model.js
src/robot/htmldata/rebot/print.css
src/robot/htmldata/rebot/report.css
src/robot/htmldata/rebot/report.html
src/robot/htmldata/rebot/testdata.js
src/robot/htmldata/rebot/util.js
src/robot/htmldata/rebot/view.js
src/robot/htmldata/testdoc/testdoc.css
src/robot/htmldata/testdoc/testdoc.html
src/robot/libdocpkg/__init__.py
src/robot/libdocpkg/builder.py
src/robot/libdocpkg/consoleviewer.py
src/robotframework_4.0.2.dev1_orth_2021.egg-info/PKG-INFO
src/robotframework_4.0.2.dev1_orth_2021.egg-info/SOURCES.txt
src/robotframework_4.0.2.dev1_orth_2021.egg-info/dependency_links.txt
src/robotframework_4.0.2.dev1_orth_2021.egg-info/entry_points.txt
src/robotframework_4.0.2.dev1_orth_2021.egg-info/top_level.txt