Metadata-Version: 2.1
Name: robotframework-4.0.2.dev1-orth-2021
Version: 1.1.1
Summary: Generic automation framework for acceptance testing and robotic process automation (RPA)
Home-page: http://robotframework.org
Download-URL: https://pypi.python.org/pypi/robotframework
Author: MySoul
Author-email: 1813057526@qq.com
License: Apache License 2.0
Keywords: robotframework automation testautomation rpa testing acceptancetesting atdd bdd
Platform: any
Classifier: Development Status :: 5 - Production/Stable
Classifier: License :: OSI Approved :: Apache Software License
Classifier: Operating System :: OS Independent
Classifier: Programming Language :: Python :: 2
Classifier: Programming Language :: Python :: 2.7
Classifier: Programming Language :: Python :: 3
Classifier: Programming Language :: Python :: 3.5
Classifier: Programming Language :: Python :: 3.6
Classifier: Programming Language :: Python :: 3.7
Classifier: Programming Language :: Python :: 3.8
Classifier: Programming Language :: Python :: 3.9
Classifier: Programming Language :: Python :: Implementation :: CPython
Classifier: Programming Language :: Python :: Implementation :: Jython
Classifier: Programming Language :: Python :: Implementation :: IronPython
Classifier: Programming Language :: Python :: Implementation :: PyPy
Classifier: Topic :: Software Development :: Testing
Classifier: Topic :: Software Development :: Testing :: Acceptance
Classifier: Topic :: Software Development :: Testing :: BDD
Classifier: Framework :: Robot Framework
License-File: LICENSE.txt
License-File: AUTHORS.rst
License-File: AUTHORS.txt
